[
    {
        "id": "14276976",
        "date": "2023-09-27 17:30:00",
        "end_date": "2023-09-27 17:45:23",
        "tournament_id": "33714",
        "T1": "2010",
        "T2": "2155",
        "S1": "0",
        "S2": "3",
        "PS": "6:11 - 9:11 - 11:13 - 0:0 - 0:0",
        "St": "4",
        "ES": "0",
        "hash": "8ff7adad7bff4f09ae320d0062197e42",
        "status": "0",
        "youtube_Id": "LQ-JbU8B0sM",
        "createdAt": "2023-09-26 16:38:20",
        "player_1": "Darbinyan Armen",
        "player_1_url": "https://stats.sportgenerate.com/player/darbinyan-armen/",
        "player_2": "Petrosyan Davit",
        "player_2_url": "https://stats.sportgenerate.com/player/petrosyan-davit/"
    },
    {
        "id": "14276975",
        "date": "2023-09-27 17:20:00",
        "end_date": "2023-09-27 17:34:02",
        "tournament_id": "33714",
        "T1": "986",
        "T2": "987",
        "S1": "3",
        "S2": "0",
        "PS": "11:9 - 12:10 - 11:4 - 0:0 - 0:0",
        "St": "4",
        "ES": "111878",
        "hash": "17bea9bd92906af80c95e048cfade11b",
        "status": "0",
        "youtube_Id": "UYA-4b6C0DQ",
        "createdAt": "2023-09-26 16:38:20",
        "player_1": "Mkrtchyan Andranik",
        "player_1_url": "https://stats.sportgenerate.com/player/mkrtchyan-andranik/",
        "player_2": "Avakimyan Davit",
        "player_2_url": "https://stats.sportgenerate.com/player/avakimyan-davit/"
    },
    {
        "id": "14276964",
        "date": "2023-09-27 17:00:00",
        "end_date": "2023-09-27 17:12:05",
        "tournament_id": "33714",
        "T1": "1970",
        "T2": "2010",
        "S1": "3",
        "S2": "0",
        "PS": "11:8 - 11:7 - 11:9 - 0:0 - 0:0",
        "St": "4",
        "ES": "0",
        "hash": "091f986c03011f20e669f71f3b6ee0d6",
        "status": "0",
        "youtube_Id": "rmCIyoGecuA",
        "createdAt": "2023-09-26 16:38:20",
        "player_1": "Gevorgyan Hayk",
        "player_1_url": "https://stats.sportgenerate.com/player/gevorgyan-hayk/",
        "player_2": "Darbinyan Armen",
        "player_2_url": "https://stats.sportgenerate.com/player/darbinyan-armen/"
    },
    {
        "id": "14276962",
        "date": "2023-09-27 16:45:00",
        "end_date": "2023-09-27 17:12:25",
        "tournament_id": "33714",
        "T1": "986",
        "T2": "2155",
        "S1": "2",
        "S2": "3",
        "PS": "5:11 - 11:9 - 14:12 - 7:11 - 8:11",
        "St": "4",
        "ES": "0",
        "hash": "1749343242726b1eaab4b4894d1b3906",
        "status": "0",
        "youtube_Id": "hy7MgDY9tGU",
        "createdAt": "2023-09-26 16:37:20",
        "player_1": "Mkrtchyan Andranik",
        "player_1_url": "https://stats.sportgenerate.com/player/mkrtchyan-andranik/",
        "player_2": "Petrosyan Davit",
        "player_2_url": "https://stats.sportgenerate.com/player/petrosyan-davit/"
    },
    {
        "id": "14276959",
        "date": "2023-09-27 16:30:00",
        "end_date": "2023-09-27 16:44:26",
        "tournament_id": "33714",
        "T1": "987",
        "T2": "1970",
        "S1": "1",
        "S2": "3",
        "PS": "11:7 - 9:11 - 8:11 - 6:11 - 0:0",
        "St": "4",
        "ES": "111878",
        "hash": "6471f277b098c73d66179dd758c5dc74",
        "status": "0",
        "youtube_Id": "TtduHXEzMBA",
        "createdAt": "2023-09-26 16:37:20",
        "player_1": "Avakimyan Davit",
        "player_1_url": "https://stats.sportgenerate.com/player/avakimyan-davit/",
        "player_2": "Gevorgyan Hayk",
        "player_2_url": "https://stats.sportgenerate.com/player/gevorgyan-hayk/"
    },
    {
        "id": "14276957",
        "date": "2023-09-27 16:15:00",
        "end_date": "2023-09-27 16:27:03",
        "tournament_id": "33714",
        "T1": "2010",
        "T2": "986",
        "S1": "0",
        "S2": "3",
        "PS": "9:11 - 8:11 - 6:11 - 0:0 - 0:0",
        "St": "4",
        "ES": "0",
        "hash": "8e6abc881df9aff22263da849124658d",
        "status": "0",
        "youtube_Id": "SfBaNCUtZ3o",
        "createdAt": "2023-09-26 16:37:20",
        "player_1": "Darbinyan Armen",
        "player_1_url": "https://stats.sportgenerate.com/player/darbinyan-armen/",
        "player_2": "Mkrtchyan Andranik",
        "player_2_url": "https://stats.sportgenerate.com/player/mkrtchyan-andranik/"
    },
    {
        "id": "14276956",
        "date": "2023-09-27 16:00:00",
        "end_date": "2023-09-27 16:21:24",
        "tournament_id": "33714",
        "T1": "2155",
        "T2": "1970",
        "S1": "1",
        "S2": "3",
        "PS": "11:8 - 10:12 - 13:15 - 9:11 - 0:0",
        "St": "4",
        "ES": "0",
        "hash": "d128b100166d882f97e0f6369a48bb1f",
        "status": "0",
        "youtube_Id": "83f4HFK7UfU",
        "createdAt": "2023-09-26 16:36:19",
        "player_1": "Petrosyan Davit",
        "player_1_url": "https://stats.sportgenerate.com/player/petrosyan-davit/",
        "player_2": "Gevorgyan Hayk",
        "player_2_url": "https://stats.sportgenerate.com/player/gevorgyan-hayk/"
    },
    {
        "id": "14276926",
        "date": "2023-09-27 15:45:00",
        "end_date": "2023-09-27 16:01:40",
        "tournament_id": "33714",
        "T1": "987",
        "T2": "2010",
        "S1": "3",
        "S2": "2",
        "PS": "5:11 - 11:5 - 11:8 - 4:11 - 11:5",
        "St": "4",
        "ES": "111878",
        "hash": "c3d2d3f070a297eef3061c07f6120e4f",
        "status": "0",
        "youtube_Id": "0Jd7zLdxlBI",
        "createdAt": "2023-09-26 16:35:19",
        "player_1": "Avakimyan Davit",
        "player_1_url": "https://stats.sportgenerate.com/player/avakimyan-davit/",
        "player_2": "Darbinyan Armen",
        "player_2_url": "https://stats.sportgenerate.com/player/darbinyan-armen/"
    },
    {
        "id": "14276923",
        "date": "2023-09-27 15:30:00",
        "end_date": "2023-09-27 15:45:45",
        "tournament_id": "33714",
        "T1": "1970",
        "T2": "986",
        "S1": "1",
        "S2": "3",
        "PS": "13:11 - 3:11 - 3:11 - 5:11 - 0:0",
        "St": "4",
        "ES": "111878",
        "hash": "be6dacad99f03aeec5d686b7fa27ed81",
        "status": "0",
        "youtube_Id": "tIeoRWWYcfw",
        "createdAt": "2023-09-26 16:35:19",
        "player_1": "Gevorgyan Hayk",
        "player_1_url": "https://stats.sportgenerate.com/player/gevorgyan-hayk/",
        "player_2": "Mkrtchyan Andranik",
        "player_2_url": "https://stats.sportgenerate.com/player/mkrtchyan-andranik/"
    },
    {
        "id": "14276912",
        "date": "2023-09-27 15:15:00",
        "end_date": "2023-09-27 15:35:09",
        "tournament_id": "33714",
        "T1": "2155",
        "T2": "987",
        "S1": "3",
        "S2": "1",
        "PS": "17:15 - 7:11 - 12:10 - 11:4 - 0:0",
        "St": "4",
        "ES": "0",
        "hash": "282539b87a8f5ce7743969c719cd313b",
        "status": "0",
        "youtube_Id": "CZ9MnAQCAuI",
        "createdAt": "2023-09-26 16:34:19",
        "player_1": "Petrosyan Davit",
        "player_1_url": "https://stats.sportgenerate.com/player/petrosyan-davit/",
        "player_2": "Avakimyan Davit",
        "player_2_url": "https://stats.sportgenerate.com/player/avakimyan-davit/"
    },
    {
        "id": "14276900",
        "date": "2023-09-27 15:00:00",
        "end_date": "2023-09-27 15:11:06",
        "tournament_id": "33714",
        "T1": "989",
        "T2": "2497",
        "S1": "0",
        "S2": "3",
        "PS": "7:11 - 2:11 - 6:11 - 0:0 - 0:0",
        "St": "4",
        "ES": "111878",
        "hash": "20d2cf1a95e56d92f67dfa63279843ec",
        "status": "0",
        "youtube_Id": "XFZnj1-yA1A",
        "createdAt": "2023-09-26 16:33:19",
        "player_1": "Nikoghosyan Narek",
        "player_1_url": "https://stats.sportgenerate.com/player/nikoghosyan-narek/",
        "player_2": "Rafayelyan Edgar",
        "player_2_url": "https://stats.sportgenerate.com/player/rafayelyan-edgar/"
    },
    {
        "id": "14276894",
        "date": "2023-09-27 14:45:00",
        "end_date": "2023-09-27 15:06:15",
        "tournament_id": "33714",
        "T1": "990",
        "T2": "995",
        "S1": "3",
        "S2": "1",
        "PS": "11:8 - 5:11 - 11:4 - 11:8 - 0:0",
        "St": "4",
        "ES": "0",
        "hash": "7f57b23b35012adbc06d230cd23d764b",
        "status": "0",
        "youtube_Id": "fwAIbu_jDt8",
        "createdAt": "2023-09-26 16:33:19",
        "player_1": "Antonyan Eduard",
        "player_1_url": "https://stats.sportgenerate.com/player/antonyan-eduard/",
        "player_2": "Papyan Karen",
        "player_2_url": "https://stats.sportgenerate.com/player/papyan-karen/"
    },
    {
        "id": "14276890",
        "date": "2023-09-27 14:30:00",
        "end_date": "2023-09-27 14:47:21",
        "tournament_id": "33714",
        "T1": "991",
        "T2": "989",
        "S1": "3",
        "S2": "0",
        "PS": "12:10 - 11:4 - 16:14 - 0:0 - 0:0",
        "St": "4",
        "ES": "0",
        "hash": "35e356d1e99095f7eb97d55aeae5713b",
        "status": "0",
        "youtube_Id": "sS0ATy_x2ug",
        "createdAt": "2023-09-26 16:32:19",
        "player_1": "Diaryan Aleksandr",
        "player_1_url": "https://stats.sportgenerate.com/player/diaryan-aleksandr/",
        "player_2": "Nikoghosyan Narek",
        "player_2_url": "https://stats.sportgenerate.com/player/nikoghosyan-narek/"
    },
    {
        "id": "14276878",
        "date": "2023-09-27 14:15:00",
        "end_date": "2023-09-27 14:31:59",
        "tournament_id": "33714",
        "T1": "2497",
        "T2": "990",
        "S1": "3",
        "S2": "0",
        "PS": "11:5 - 11:7 - 11:4 - 0:0 - 0:0",
        "St": "4",
        "ES": "0",
        "hash": "fcb150bde33a2d2d8a35a440c8926e83",
        "status": "0",
        "youtube_Id": "ox_Jta5MY24",
        "createdAt": "2023-09-26 16:32:19",
        "player_1": "Rafayelyan Edgar",
        "player_1_url": "https://stats.sportgenerate.com/player/rafayelyan-edgar/",
        "player_2": "Antonyan Eduard",
        "player_2_url": "https://stats.sportgenerate.com/player/antonyan-eduard/"
    },
    {
        "id": "14276876",
        "date": "2023-09-27 14:00:00",
        "end_date": "2023-09-27 14:15:23",
        "tournament_id": "33714",
        "T1": "991",
        "T2": "995",
        "S1": "3",
        "S2": "0",
        "PS": "11:3 - 11:7 - 11:7 - 0:0 - 0:0",
        "St": "4",
        "ES": "0",
        "hash": "57519c1a938a0cd69369a5b2027d5b6a",
        "status": "0",
        "youtube_Id": "e-kVJxbCefk",
        "createdAt": "2023-09-26 16:32:19",
        "player_1": "Diaryan Aleksandr",
        "player_1_url": "https://stats.sportgenerate.com/player/diaryan-aleksandr/",
        "player_2": "Papyan Karen",
        "player_2_url": "https://stats.sportgenerate.com/player/papyan-karen/"
    },
    {
        "id": "14276874",
        "date": "2023-09-27 13:50:00",
        "end_date": "2023-09-27 14:05:24",
        "tournament_id": "33714",
        "T1": "989",
        "T2": "990",
        "S1": "0",
        "S2": "3",
        "PS": "3:11 - 5:11 - 10:12 - 0:0 - 0:0",
        "St": "4",
        "ES": "0",
        "hash": "4f844822a961e85f6fe156b8eba86980",
        "status": "0",
        "youtube_Id": "n9vr_Nptv4M",
        "createdAt": "2023-09-26 16:31:19",
        "player_1": "Nikoghosyan Narek",
        "player_1_url": "https://stats.sportgenerate.com/player/nikoghosyan-narek/",
        "player_2": "Antonyan Eduard",
        "player_2_url": "https://stats.sportgenerate.com/player/antonyan-eduard/"
    },
    {
        "id": "14276868",
        "date": "2023-09-27 13:30:00",
        "end_date": "2023-09-27 13:54:46",
        "tournament_id": "33714",
        "T1": "2497",
        "T2": "991",
        "S1": "2",
        "S2": "3",
        "PS": "5:11 - 9:11 - 11:6 - 11:1 - 9:11",
        "St": "4",
        "ES": "111878",
        "hash": "808b7836458814aa8f0b2bbe5b2f2cf0",
        "status": "0",
        "youtube_Id": "PDgf81CRalQ",
        "createdAt": "2023-09-26 16:31:19",
        "player_1": "Rafayelyan Edgar",
        "player_1_url": "https://stats.sportgenerate.com/player/rafayelyan-edgar/",
        "player_2": "Diaryan Aleksandr",
        "player_2_url": "https://stats.sportgenerate.com/player/diaryan-aleksandr/"
    },
    {
        "id": "14276867",
        "date": "2023-09-27 13:15:00",
        "end_date": "2023-09-27 13:37:15",
        "tournament_id": "33714",
        "T1": "995",
        "T2": "989",
        "S1": "3",
        "S2": "1",
        "PS": "6:11 - 11:2 - 11:8 - 11:9 - 0:0",
        "St": "4",
        "ES": "0",
        "hash": "7c7c9e23f365fa2c07691d5333107d7b",
        "status": "0",
        "youtube_Id": "F8iTSua6EsA",
        "createdAt": "2023-09-26 16:30:19",
        "player_1": "Papyan Karen",
        "player_1_url": "https://stats.sportgenerate.com/player/papyan-karen/",
        "player_2": "Nikoghosyan Narek",
        "player_2_url": "https://stats.sportgenerate.com/player/nikoghosyan-narek/"
    },
    {
        "id": "14276856",
        "date": "2023-09-27 13:05:00",
        "end_date": "2023-09-27 13:18:17",
        "tournament_id": "33714",
        "T1": "990",
        "T2": "991",
        "S1": "0",
        "S2": "3",
        "PS": "3:11 - 2:11 - 4:11 - 0:0 - 0:0",
        "St": "4",
        "ES": "0",
        "hash": "53981e943cf41e828a4a08e59bfc0ed4",
        "status": "0",
        "youtube_Id": "LSA3xQswUtQ",
        "createdAt": "2023-09-26 16:30:19",
        "player_1": "Antonyan Eduard",
        "player_1_url": "https://stats.sportgenerate.com/player/antonyan-eduard/",
        "player_2": "Diaryan Aleksandr",
        "player_2_url": "https://stats.sportgenerate.com/player/diaryan-aleksandr/"
    },
    {
        "id": "14276851",
        "date": "2023-09-27 12:55:00",
        "end_date": "2023-09-27 13:06:14",
        "tournament_id": "33714",
        "T1": "995",
        "T2": "2497",
        "S1": "0",
        "S2": "3",
        "PS": "7:11 - 6:11 - 8:11 - 0:0 - 0:0",
        "St": "4",
        "ES": "111878",
        "hash": "45fc3435262dc2a2a33ae8f5e1b1d5ac",
        "status": "0",
        "youtube_Id": "KaW9bgZzQOk",
        "createdAt": "2023-09-26 16:29:19",
        "player_1": "Papyan Karen",
        "player_1_url": "https://stats.sportgenerate.com/player/papyan-karen/",
        "player_2": "Rafayelyan Edgar",
        "player_2_url": "https://stats.sportgenerate.com/player/rafayelyan-edgar/"
    },
    {
        "id": "14276843",
        "date": "2023-09-27 12:25:00",
        "end_date": "2023-09-27 12:50:33",
        "tournament_id": "33714",
        "T1": "989",
        "T2": "991",
        "S1": "1",
        "S2": "3",
        "PS": "14:12 - 8:11 - 6:11 - 3:11 - 0:0",
        "St": "4",
        "ES": "0",
        "hash": "2baac00ec12934f153b7f5313ebdb207",
        "status": "0",
        "youtube_Id": "gAIEt4gyifo",
        "createdAt": "2023-09-26 16:29:19",
        "player_1": "Nikoghosyan Narek",
        "player_1_url": "https://stats.sportgenerate.com/player/nikoghosyan-narek/",
        "player_2": "Diaryan Aleksandr",
        "player_2_url": "https://stats.sportgenerate.com/player/diaryan-aleksandr/"
    },
    {
        "id": "14276837",
        "date": "2023-09-27 12:10:00",
        "end_date": "2023-09-27 12:37:11",
        "tournament_id": "33714",
        "T1": "995",
        "T2": "990",
        "S1": "3",
        "S2": "2",
        "PS": "11:7 - 4:11 - 11:6 - 4:11 - 11:6",
        "St": "4",
        "ES": "0",
        "hash": "17361a968c3451f56d907b4ddeac42db",
        "status": "0",
        "youtube_Id": "WAh1poq0qFc",
        "createdAt": "2023-09-26 16:29:19",
        "player_1": "Papyan Karen",
        "player_1_url": "https://stats.sportgenerate.com/player/papyan-karen/",
        "player_2": "Antonyan Eduard",
        "player_2_url": "https://stats.sportgenerate.com/player/antonyan-eduard/"
    },
    {
        "id": "14276826",
        "date": "2023-09-27 11:50:00",
        "end_date": "2023-09-27 12:16:50",
        "tournament_id": "33714",
        "T1": "2497",
        "T2": "989",
        "S1": "3",
        "S2": "2",
        "PS": "11:7 - 6:11 - 12:10 - 5:11 - 11:5",
        "St": "4",
        "ES": "111878",
        "hash": "113fd956b251a590157f12dbe5104625",
        "status": "0",
        "youtube_Id": "FJOiSCTS5RE",
        "createdAt": "2023-09-26 16:28:19",
        "player_1": "Rafayelyan Edgar",
        "player_1_url": "https://stats.sportgenerate.com/player/rafayelyan-edgar/",
        "player_2": "Nikoghosyan Narek",
        "player_2_url": "https://stats.sportgenerate.com/player/nikoghosyan-narek/"
    },
    {
        "id": "14276821",
        "date": "2023-09-27 11:40:00",
        "end_date": "2023-09-27 12:17:59",
        "tournament_id": "33714",
        "T1": "995",
        "T2": "991",
        "S1": "3",
        "S2": "2",
        "PS": "8:11 - 11:9 - 9:11 - 15:13 - 11:9",
        "St": "4",
        "ES": "0",
        "hash": "2f8dea0e3ab967d686caf01b365e1ae1",
        "status": "0",
        "youtube_Id": "ynOyxru2Zjs",
        "createdAt": "2023-09-26 16:28:19",
        "player_1": "Papyan Karen",
        "player_1_url": "https://stats.sportgenerate.com/player/papyan-karen/",
        "player_2": "Diaryan Aleksandr",
        "player_2_url": "https://stats.sportgenerate.com/player/diaryan-aleksandr/"
    },
    {
        "id": "14276816",
        "date": "2023-09-27 11:15:00",
        "end_date": "2023-09-27 11:39:35",
        "tournament_id": "33714",
        "T1": "990",
        "T2": "2497",
        "S1": "3",
        "S2": "1",
        "PS": "7:11 - 11:5 - 15:13 - 12:10 - 0:0",
        "St": "4",
        "ES": "0",
        "hash": "986e851643ccaeccabc5f64174f430f3",
        "status": "0",
        "youtube_Id": "3AWgG_E0GXU",
        "createdAt": "2023-09-26 16:27:19",
        "player_1": "Antonyan Eduard",
        "player_1_url": "https://stats.sportgenerate.com/player/antonyan-eduard/",
        "player_2": "Rafayelyan Edgar",
        "player_2_url": "https://stats.sportgenerate.com/player/rafayelyan-edgar/"
    },
    {
        "id": "14276811",
        "date": "2023-09-27 11:00:00",
        "end_date": "2023-09-27 11:28:22",
        "tournament_id": "33714",
        "T1": "989",
        "T2": "995",
        "S1": "2",
        "S2": "3",
        "PS": "11:6 - 11:4 - 5:11 - 10:12 - 11:13",
        "St": "4",
        "ES": "111878",
        "hash": "bb21b0d60f7350a14a40f1f4c07b9b9b",
        "status": "0",
        "youtube_Id": "RZUyJtd1hfg",
        "createdAt": "2023-09-26 16:27:19",
        "player_1": "Nikoghosyan Narek",
        "player_1_url": "https://stats.sportgenerate.com/player/nikoghosyan-narek/",
        "player_2": "Papyan Karen",
        "player_2_url": "https://stats.sportgenerate.com/player/papyan-karen/"
    },
    {
        "id": "14276808",
        "date": "2023-09-27 10:45:00",
        "end_date": "2023-09-27 11:07:34",
        "tournament_id": "33714",
        "T1": "991",
        "T2": "2497",
        "S1": "3",
        "S2": "2",
        "PS": "11:8 - 8:11 - 11:1 - 6:11 - 11:4",
        "St": "4",
        "ES": "0",
        "hash": "9aaa19f457e48b796cbc6930bdf4cff7",
        "status": "0",
        "youtube_Id": "KoCTI3XLRhE",
        "createdAt": "2023-09-26 16:27:19",
        "player_1": "Diaryan Aleksandr",
        "player_1_url": "https://stats.sportgenerate.com/player/diaryan-aleksandr/",
        "player_2": "Rafayelyan Edgar",
        "player_2_url": "https://stats.sportgenerate.com/player/rafayelyan-edgar/"
    },
    {
        "id": "14276807",
        "date": "2023-09-27 10:30:00",
        "end_date": "2023-09-27 10:53:20",
        "tournament_id": "33714",
        "T1": "990",
        "T2": "989",
        "S1": "1",
        "S2": "3",
        "PS": "11:5 - 11:13 - 3:11 - 5:11 - 0:0",
        "St": "4",
        "ES": "0",
        "hash": "9320fcdafa4d81741c3b19c85abfac36",
        "status": "0",
        "youtube_Id": "TKUYKQ_ZA88",
        "createdAt": "2023-09-26 16:26:18",
        "player_1": "Antonyan Eduard",
        "player_1_url": "https://stats.sportgenerate.com/player/antonyan-eduard/",
        "player_2": "Nikoghosyan Narek",
        "player_2_url": "https://stats.sportgenerate.com/player/nikoghosyan-narek/"
    },
    {
        "id": "14276735",
        "date": "2023-09-27 10:15:00",
        "end_date": "2023-09-27 10:36:47",
        "tournament_id": "33714",
        "T1": "2497",
        "T2": "995",
        "S1": "2",
        "S2": "3",
        "PS": "7:11 - 6:11 - 11:7 - 11:3 - 9:11",
        "St": "4",
        "ES": "111878",
        "hash": "b4eeb1170adeb9efe4b48db5ccc74d46",
        "status": "0",
        "youtube_Id": "fb5LNpS0FrY",
        "createdAt": "2023-09-26 16:20:20",
        "player_1": "Rafayelyan Edgar",
        "player_1_url": "https://stats.sportgenerate.com/player/rafayelyan-edgar/",
        "player_2": "Papyan Karen",
        "player_2_url": "https://stats.sportgenerate.com/player/papyan-karen/"
    },
    {
        "id": "14276734",
        "date": "2023-09-27 10:00:00",
        "end_date": "2023-09-27 10:20:01",
        "tournament_id": "33714",
        "T1": "991",
        "T2": "990",
        "S1": "3",
        "S2": "1",
        "PS": "11:8 - 11:7 - 3:11 - 11:4 - 0:0",
        "St": "4",
        "ES": "111878",
        "hash": "f6bc3ae712b129bc5848fffc53fab639",
        "status": "0",
        "youtube_Id": "rfy7pIFjB8s",
        "createdAt": "2023-09-26 16:19:19",
        "player_1": "Diaryan Aleksandr",
        "player_1_url": "https://stats.sportgenerate.com/player/diaryan-aleksandr/",
        "player_2": "Antonyan Eduard",
        "player_2_url": "https://stats.sportgenerate.com/player/antonyan-eduard/"
    }
]