[
    {
        "id": "13914085",
        "date": "2023-09-08 17:30:00",
        "end_date": null,
        "tournament_id": "33714",
        "T1": "992",
        "T2": "987",
        "S1": "0",
        "S2": "0",
        "PS": "",
        "St": "2",
        "ES": "0",
        "hash": "323a5ccb4c5283ea7242466cd2a5ffe6",
        "status": "0",
        "youtube_Id": null,
        "createdAt": "2023-09-07 14:22:16",
        "player_1": "Gevorgyan Gegham",
        "player_1_url": "https://stats.sportgenerate.com/player/gevorgyan-gegham/",
        "player_2": "Avakimyan Davit",
        "player_2_url": "https://stats.sportgenerate.com/player/avakimyan-davit/"
    },
    {
        "id": "13914066",
        "date": "2023-09-08 17:15:00",
        "end_date": "2023-09-08 17:32:48",
        "tournament_id": "33714",
        "T1": "986",
        "T2": "2010",
        "S1": "3",
        "S2": "1",
        "PS": "9:11 - 11:8 - 14:12 - 12:10 - 0:0",
        "St": "4",
        "ES": "111878",
        "hash": "3a2b0038fa782f79dff1eaf3c6491fd4",
        "status": "0",
        "youtube_Id": "naJbQcgorWE",
        "createdAt": "2023-09-07 14:22:16",
        "player_1": "Mkrtchyan Andranik",
        "player_1_url": "https://stats.sportgenerate.com/player/mkrtchyan-andranik/",
        "player_2": "Darbinyan Armen",
        "player_2_url": "https://stats.sportgenerate.com/player/darbinyan-armen/"
    },
    {
        "id": "13914055",
        "date": "2023-09-08 17:00:00",
        "end_date": null,
        "tournament_id": "33714",
        "T1": "1970",
        "T2": "992",
        "S1": "0",
        "S2": "0",
        "PS": "",
        "St": "2",
        "ES": "0",
        "hash": "f88ba0356478ab014fa93a8b00198e8c",
        "status": "0",
        "youtube_Id": null,
        "createdAt": "2023-09-07 14:22:16",
        "player_1": "Gevorgyan Hayk",
        "player_1_url": "https://stats.sportgenerate.com/player/gevorgyan-hayk/",
        "player_2": "Gevorgyan Gegham",
        "player_2_url": "https://stats.sportgenerate.com/player/gevorgyan-gegham/"
    },
    {
        "id": "13914054",
        "date": "2023-09-08 16:45:00",
        "end_date": "2023-09-08 17:05:35",
        "tournament_id": "33714",
        "T1": "986",
        "T2": "987",
        "S1": "2",
        "S2": "3",
        "PS": "7:11 - 11:3 - 5:11 - 11:8 - 8:11",
        "St": "4",
        "ES": "111878",
        "hash": "c5287e81786b8ce44d2be3630efb549b",
        "status": "0",
        "youtube_Id": null,
        "createdAt": "2023-09-07 14:22:16",
        "player_1": "Mkrtchyan Andranik",
        "player_1_url": "https://stats.sportgenerate.com/player/mkrtchyan-andranik/",
        "player_2": "Avakimyan Davit",
        "player_2_url": "https://stats.sportgenerate.com/player/avakimyan-davit/"
    },
    {
        "id": "13914039",
        "date": "2023-09-08 16:30:00",
        "end_date": "2023-09-08 16:47:28",
        "tournament_id": "33714",
        "T1": "2010",
        "T2": "1970",
        "S1": "1",
        "S2": "3",
        "PS": "11:9 - 4:11 - 8:11 - 11:13 - 0:0",
        "St": "4",
        "ES": "111878",
        "hash": "80aa53003e369585aef1cc9c8f0abf4d",
        "status": "0",
        "youtube_Id": "dXJqcBVKEI8",
        "createdAt": "2023-09-07 14:22:16",
        "player_1": "Darbinyan Armen",
        "player_1_url": "https://stats.sportgenerate.com/player/darbinyan-armen/",
        "player_2": "Gevorgyan Hayk",
        "player_2_url": "https://stats.sportgenerate.com/player/gevorgyan-hayk/"
    },
    {
        "id": "13914038",
        "date": "2023-09-08 16:15:00",
        "end_date": null,
        "tournament_id": "33714",
        "T1": "992",
        "T2": "986",
        "S1": "0",
        "S2": "0",
        "PS": "",
        "St": "2",
        "ES": "0",
        "hash": "87f7cd770583208320791f45784fe0c6",
        "status": "0",
        "youtube_Id": null,
        "createdAt": "2023-09-07 14:21:15",
        "player_1": "Gevorgyan Gegham",
        "player_1_url": "https://stats.sportgenerate.com/player/gevorgyan-gegham/",
        "player_2": "Mkrtchyan Andranik",
        "player_2_url": "https://stats.sportgenerate.com/player/mkrtchyan-andranik/"
    },
    {
        "id": "13914037",
        "date": "2023-09-08 16:00:00",
        "end_date": "2023-09-08 16:16:46",
        "tournament_id": "33714",
        "T1": "987",
        "T2": "1970",
        "S1": "3",
        "S2": "1",
        "PS": "11:9 - 12:10 - 9:11 - 11:8 - 0:0",
        "St": "4",
        "ES": "111878",
        "hash": "74b05b8fa23667505bfe378827d3a3c5",
        "status": "0",
        "youtube_Id": "qyfOS--sbKI",
        "createdAt": "2023-09-07 14:21:15",
        "player_1": "Avakimyan Davit",
        "player_1_url": "https://stats.sportgenerate.com/player/avakimyan-davit/",
        "player_2": "Gevorgyan Hayk",
        "player_2_url": "https://stats.sportgenerate.com/player/gevorgyan-hayk/"
    },
    {
        "id": "13914032",
        "date": "2023-09-08 15:45:00",
        "end_date": null,
        "tournament_id": "33714",
        "T1": "2010",
        "T2": "992",
        "S1": "0",
        "S2": "0",
        "PS": "",
        "St": "2",
        "ES": "0",
        "hash": "0c1c14c07868e447bcd5bcf8f9856a92",
        "status": "0",
        "youtube_Id": "xR7TAYU_gfY",
        "createdAt": "2023-09-07 14:21:15",
        "player_1": "Darbinyan Armen",
        "player_1_url": "https://stats.sportgenerate.com/player/darbinyan-armen/",
        "player_2": "Gevorgyan Gegham",
        "player_2_url": "https://stats.sportgenerate.com/player/gevorgyan-gegham/"
    },
    {
        "id": "13914030",
        "date": "2023-09-08 15:30:00",
        "end_date": "2023-09-08 15:41:55",
        "tournament_id": "33714",
        "T1": "1970",
        "T2": "986",
        "S1": "0",
        "S2": "3",
        "PS": "9:11 - 6:11 - 3:11 - 0:0 - 0:0",
        "St": "4",
        "ES": "111878",
        "hash": "ddd9523fcd25437393ed36d110ae05dd",
        "status": "0",
        "youtube_Id": "XRJc6onoZ5o",
        "createdAt": "2023-09-07 14:21:15",
        "player_1": "Gevorgyan Hayk",
        "player_1_url": "https://stats.sportgenerate.com/player/gevorgyan-hayk/",
        "player_2": "Mkrtchyan Andranik",
        "player_2_url": "https://stats.sportgenerate.com/player/mkrtchyan-andranik/"
    },
    {
        "id": "13914028",
        "date": "2023-09-08 15:15:00",
        "end_date": "2023-09-08 15:28:16",
        "tournament_id": "33714",
        "T1": "987",
        "T2": "2010",
        "S1": "3",
        "S2": "0",
        "PS": "11:5 - 11:8 - 11:6 - 0:0 - 0:0",
        "St": "4",
        "ES": "111878",
        "hash": "74d4a232f280165cc00592aaa9f9fe25",
        "status": "0",
        "youtube_Id": "eXjSayYZXs0",
        "createdAt": "2023-09-07 14:20:16",
        "player_1": "Avakimyan Davit",
        "player_1_url": "https://stats.sportgenerate.com/player/avakimyan-davit/",
        "player_2": "Darbinyan Armen",
        "player_2_url": "https://stats.sportgenerate.com/player/darbinyan-armen/"
    },
    {
        "id": "13914024",
        "date": "2023-09-08 15:00:00",
        "end_date": "2023-09-08 15:10:49",
        "tournament_id": "33714",
        "T1": "995",
        "T2": "991",
        "S1": "3",
        "S2": "0",
        "PS": "11:1 - 11:9 - 11:9 - 0:0 - 0:0",
        "St": "4",
        "ES": "111878",
        "hash": "2ea5164b997152e15390ecc3ed1a5d1b",
        "status": "0",
        "youtube_Id": "rQBynbEhoeo",
        "createdAt": "2023-09-07 14:20:16",
        "player_1": "Papyan Karen",
        "player_1_url": "https://stats.sportgenerate.com/player/papyan-karen/",
        "player_2": "Diaryan Aleksandr",
        "player_2_url": "https://stats.sportgenerate.com/player/diaryan-aleksandr/"
    },
    {
        "id": "13914018",
        "date": "2023-09-08 14:45:00",
        "end_date": "2023-09-08 15:15:46",
        "tournament_id": "33714",
        "T1": "989",
        "T2": "1365",
        "S1": "2",
        "S2": "3",
        "PS": "8:11 - 11:8 - 5:11 - 11:9 - 11:13",
        "St": "4",
        "ES": "0",
        "hash": "f1ef60405030ad375cacf9657329cfe3",
        "status": "0",
        "youtube_Id": "yqBgmgCnbUM",
        "createdAt": "2023-09-07 14:20:16",
        "player_1": "Nikoghosyan Narek",
        "player_1_url": "https://stats.sportgenerate.com/player/nikoghosyan-narek/",
        "player_2": "Soghomonyan Hrayr",
        "player_2_url": "https://stats.sportgenerate.com/player/soghomonyan-hrayr/"
    },
    {
        "id": "13914008",
        "date": "2023-09-08 14:30:00",
        "end_date": "2023-09-08 14:47:56",
        "tournament_id": "33714",
        "T1": "994",
        "T2": "995",
        "S1": "1",
        "S2": "3",
        "PS": "13:15 - 11:4 - 9:11 - 7:11 - 0:0",
        "St": "4",
        "ES": "111878",
        "hash": "f5ee4c8d8bef02d527ddb62a9494aa8b",
        "status": "0",
        "youtube_Id": "yYOVxRAmRfU",
        "createdAt": "2023-09-07 14:20:16",
        "player_1": "Nazaryan Mushegh",
        "player_1_url": "https://stats.sportgenerate.com/player/nazaryan-mushegh/",
        "player_2": "Papyan Karen",
        "player_2_url": "https://stats.sportgenerate.com/player/papyan-karen/"
    },
    {
        "id": "13914006",
        "date": "2023-09-08 14:20:00",
        "end_date": "2023-09-08 14:39:14",
        "tournament_id": "33714",
        "T1": "991",
        "T2": "989",
        "S1": "3",
        "S2": "0",
        "PS": "11:8 - 11:7 - 11:9 - 0:0 - 0:0",
        "St": "4",
        "ES": "0",
        "hash": "dbcc84ec0c9df77b90a2ec0444428dcb",
        "status": "0",
        "youtube_Id": "MhHEANkPud8",
        "createdAt": "2023-09-07 14:19:17",
        "player_1": "Diaryan Aleksandr",
        "player_1_url": "https://stats.sportgenerate.com/player/diaryan-aleksandr/",
        "player_2": "Nikoghosyan Narek",
        "player_2_url": "https://stats.sportgenerate.com/player/nikoghosyan-narek/"
    },
    {
        "id": "13914005",
        "date": "2023-09-08 14:00:00",
        "end_date": "2023-09-08 14:12:50",
        "tournament_id": "33714",
        "T1": "994",
        "T2": "1365",
        "S1": "3",
        "S2": "0",
        "PS": "11:5 - 11:7 - 11:7 - 0:0 - 0:0",
        "St": "4",
        "ES": "111878",
        "hash": "507234dff3b67edc58b9756a70e12ee9",
        "status": "0",
        "youtube_Id": "aJXDQ9x_jDU",
        "createdAt": "2023-09-07 14:19:17",
        "player_1": "Nazaryan Mushegh",
        "player_1_url": "https://stats.sportgenerate.com/player/nazaryan-mushegh/",
        "player_2": "Soghomonyan Hrayr",
        "player_2_url": "https://stats.sportgenerate.com/player/soghomonyan-hrayr/"
    },
    {
        "id": "13913979",
        "date": "2023-09-08 13:45:00",
        "end_date": "2023-09-08 14:10:33",
        "tournament_id": "33714",
        "T1": "995",
        "T2": "989",
        "S1": "1",
        "S2": "3",
        "PS": "10:12 - 11:8 - 8:11 - 9:11 - 0:0",
        "St": "4",
        "ES": "0",
        "hash": "c1391e13caeff83f8c117be88ece7229",
        "status": "0",
        "youtube_Id": "2jx7UOVfMcM",
        "createdAt": "2023-09-07 14:19:17",
        "player_1": "Papyan Karen",
        "player_1_url": "https://stats.sportgenerate.com/player/papyan-karen/",
        "player_2": "Nikoghosyan Narek",
        "player_2_url": "https://stats.sportgenerate.com/player/nikoghosyan-narek/"
    },
    {
        "id": "13913977",
        "date": "2023-09-08 13:30:00",
        "end_date": "2023-09-08 13:42:15",
        "tournament_id": "33714",
        "T1": "991",
        "T2": "994",
        "S1": "3",
        "S2": "0",
        "PS": "11:7 - 11:5 - 11:4 - 0:0 - 0:0",
        "St": "4",
        "ES": "0",
        "hash": "e839032bb47beef1855ed09a981b2431",
        "status": "0",
        "youtube_Id": "fgKaRKamkMk",
        "createdAt": "2023-09-07 14:18:16",
        "player_1": "Diaryan Aleksandr",
        "player_1_url": "https://stats.sportgenerate.com/player/diaryan-aleksandr/",
        "player_2": "Nazaryan Mushegh",
        "player_2_url": "https://stats.sportgenerate.com/player/nazaryan-mushegh/"
    },
    {
        "id": "13913976",
        "date": "2023-09-08 13:15:00",
        "end_date": "2023-09-08 13:28:42",
        "tournament_id": "33714",
        "T1": "1365",
        "T2": "995",
        "S1": "0",
        "S2": "3",
        "PS": "8:11 - 11:13 - 5:11 - 0:0 - 0:0",
        "St": "4",
        "ES": "0",
        "hash": "d8a4a7d627343272640c78be384a6bc6",
        "status": "0",
        "youtube_Id": "PprP89dFvuA",
        "createdAt": "2023-09-07 14:18:16",
        "player_1": "Soghomonyan Hrayr",
        "player_1_url": "https://stats.sportgenerate.com/player/soghomonyan-hrayr/",
        "player_2": "Papyan Karen",
        "player_2_url": "https://stats.sportgenerate.com/player/papyan-karen/"
    },
    {
        "id": "13913965",
        "date": "2023-09-08 13:00:00",
        "end_date": "2023-09-08 13:12:21",
        "tournament_id": "33714",
        "T1": "989",
        "T2": "994",
        "S1": "3",
        "S2": "0",
        "PS": "11:9 - 11:6 - 11:4 - 0:0 - 0:0",
        "St": "4",
        "ES": "111878",
        "hash": "1b309aa10fa86671fc9d5ff92b657a8a",
        "status": "0",
        "youtube_Id": "71El6rfwQzA",
        "createdAt": "2023-09-07 14:18:16",
        "player_1": "Nikoghosyan Narek",
        "player_1_url": "https://stats.sportgenerate.com/player/nikoghosyan-narek/",
        "player_2": "Nazaryan Mushegh",
        "player_2_url": "https://stats.sportgenerate.com/player/nazaryan-mushegh/"
    },
    {
        "id": "13913964",
        "date": "2023-09-08 12:45:00",
        "end_date": "2023-09-08 13:03:26",
        "tournament_id": "33714",
        "T1": "1365",
        "T2": "991",
        "S1": "0",
        "S2": "3",
        "PS": "11:13 - 9:11 - 10:12 - 0:0 - 0:0",
        "St": "4",
        "ES": "111878",
        "hash": "44e1330c69290e98b28fb4499638f2df",
        "status": "0",
        "youtube_Id": "UcTWnQSOhW4",
        "createdAt": "2023-09-07 14:18:16",
        "player_1": "Soghomonyan Hrayr",
        "player_1_url": "https://stats.sportgenerate.com/player/soghomonyan-hrayr/",
        "player_2": "Diaryan Aleksandr",
        "player_2_url": "https://stats.sportgenerate.com/player/diaryan-aleksandr/"
    },
    {
        "id": "13913961",
        "date": "2023-09-08 12:15:00",
        "end_date": "2023-09-08 12:38:28",
        "tournament_id": "33714",
        "T1": "995",
        "T2": "994",
        "S1": "2",
        "S2": "3",
        "PS": "8:11 - 11:9 - 6:11 - 11:8 - 8:11",
        "St": "4",
        "ES": "0",
        "hash": "1d2fd5432d9c63ec9da7872857658175",
        "status": "0",
        "youtube_Id": null,
        "createdAt": "2023-09-07 14:17:16",
        "player_1": "Papyan Karen",
        "player_1_url": "https://stats.sportgenerate.com/player/papyan-karen/",
        "player_2": "Nazaryan Mushegh",
        "player_2_url": "https://stats.sportgenerate.com/player/nazaryan-mushegh/"
    },
    {
        "id": "13913960",
        "date": "2023-09-08 12:00:00",
        "end_date": "2023-09-08 12:26:40",
        "tournament_id": "33714",
        "T1": "1365",
        "T2": "989",
        "S1": "2",
        "S2": "3",
        "PS": "11:6 - 12:10 - 8:11 - 7:11 - 2:11",
        "St": "4",
        "ES": "111878",
        "hash": "76a05ee3dc2e6673c14891eacce93170",
        "status": "0",
        "youtube_Id": "kD16vFxdFF0",
        "createdAt": "2023-09-07 14:17:16",
        "player_1": "Soghomonyan Hrayr",
        "player_1_url": "https://stats.sportgenerate.com/player/soghomonyan-hrayr/",
        "player_2": "Nikoghosyan Narek",
        "player_2_url": "https://stats.sportgenerate.com/player/nikoghosyan-narek/"
    },
    {
        "id": "13913959",
        "date": "2023-09-08 11:55:00",
        "end_date": "2023-09-08 12:06:32",
        "tournament_id": "33714",
        "T1": "991",
        "T2": "995",
        "S1": "0",
        "S2": "3",
        "PS": "6:11 - 6:11 - 7:11 - 0:0 - 0:0",
        "St": "4",
        "ES": "111878",
        "hash": "e254252adbdc6f70388ca88c8d6ddb81",
        "status": "0",
        "youtube_Id": "r1N4PQto3hg",
        "createdAt": "2023-09-07 14:17:16",
        "player_1": "Diaryan Aleksandr",
        "player_1_url": "https://stats.sportgenerate.com/player/diaryan-aleksandr/",
        "player_2": "Papyan Karen",
        "player_2_url": "https://stats.sportgenerate.com/player/papyan-karen/"
    },
    {
        "id": "13913956",
        "date": "2023-09-08 11:30:00",
        "end_date": "2023-09-08 11:42:07",
        "tournament_id": "33714",
        "T1": "1365",
        "T2": "994",
        "S1": "3",
        "S2": "0",
        "PS": "11:6 - 11:5 - 11:6 - 0:0 - 0:0",
        "St": "4",
        "ES": "0",
        "hash": "024fa0bc894beadfc23055dcc8ee556a",
        "status": "0",
        "youtube_Id": "o4IJ4PXdzlo",
        "createdAt": "2023-09-07 14:17:16",
        "player_1": "Soghomonyan Hrayr",
        "player_1_url": "https://stats.sportgenerate.com/player/soghomonyan-hrayr/",
        "player_2": "Nazaryan Mushegh",
        "player_2_url": "https://stats.sportgenerate.com/player/nazaryan-mushegh/"
    },
    {
        "id": "13913954",
        "date": "2023-09-08 11:15:00",
        "end_date": "2023-09-08 11:46:54",
        "tournament_id": "33714",
        "T1": "989",
        "T2": "991",
        "S1": "3",
        "S2": "2",
        "PS": "11:7 - 11:7 - 9:11 - 11:13 - 11:7",
        "St": "4",
        "ES": "111878",
        "hash": "4cd9873c36e010d1b4dc895a88f2deab",
        "status": "0",
        "youtube_Id": "6ySHUI0skNs",
        "createdAt": "2023-09-07 14:16:15",
        "player_1": "Nikoghosyan Narek",
        "player_1_url": "https://stats.sportgenerate.com/player/nikoghosyan-narek/",
        "player_2": "Diaryan Aleksandr",
        "player_2_url": "https://stats.sportgenerate.com/player/diaryan-aleksandr/"
    },
    {
        "id": "13913953",
        "date": "2023-09-08 11:00:00",
        "end_date": "2023-09-08 11:13:00",
        "tournament_id": "33714",
        "T1": "995",
        "T2": "1365",
        "S1": "3",
        "S2": "0",
        "PS": "11:8 - 11:9 - 11:4 - 0:0 - 0:0",
        "St": "4",
        "ES": "111878",
        "hash": "b273bf4e201baf562bb741acc61a3f75",
        "status": "0",
        "youtube_Id": "JD0w4Bi8db4",
        "createdAt": "2023-09-07 14:16:15",
        "player_1": "Papyan Karen",
        "player_1_url": "https://stats.sportgenerate.com/player/papyan-karen/",
        "player_2": "Soghomonyan Hrayr",
        "player_2_url": "https://stats.sportgenerate.com/player/soghomonyan-hrayr/"
    },
    {
        "id": "13913952",
        "date": "2023-09-08 10:45:00",
        "end_date": "2023-09-08 10:59:37",
        "tournament_id": "33714",
        "T1": "994",
        "T2": "991",
        "S1": "0",
        "S2": "3",
        "PS": "8:11 - 9:11 - 9:11 - 0:0 - 0:0",
        "St": "4",
        "ES": "0",
        "hash": "c9eb25f0c90ec8f6f9533fc94b561073",
        "status": "0",
        "youtube_Id": "ijH8nw2oTE8",
        "createdAt": "2023-09-07 14:16:15",
        "player_1": "Nazaryan Mushegh",
        "player_1_url": "https://stats.sportgenerate.com/player/nazaryan-mushegh/",
        "player_2": "Diaryan Aleksandr",
        "player_2_url": "https://stats.sportgenerate.com/player/diaryan-aleksandr/"
    },
    {
        "id": "13913951",
        "date": "2023-09-08 10:30:00",
        "end_date": "2023-09-08 10:54:33",
        "tournament_id": "33714",
        "T1": "989",
        "T2": "995",
        "S1": "1",
        "S2": "3",
        "PS": "8:11 - 10:12 - 11:5 - 8:11 - 0:0",
        "St": "4",
        "ES": "111878",
        "hash": "c1d2ebab441dd6c405c3cf8f6488ebf7",
        "status": "0",
        "youtube_Id": "MdIFBD_dewM",
        "createdAt": "2023-09-07 14:16:15",
        "player_1": "Nikoghosyan Narek",
        "player_1_url": "https://stats.sportgenerate.com/player/nikoghosyan-narek/",
        "player_2": "Papyan Karen",
        "player_2_url": "https://stats.sportgenerate.com/player/papyan-karen/"
    },
    {
        "id": "13913939",
        "date": "2023-09-08 10:15:00",
        "end_date": "2023-09-08 10:38:19",
        "tournament_id": "33714",
        "T1": "991",
        "T2": "1365",
        "S1": "3",
        "S2": "2",
        "PS": "7:11 - 11:13 - 11:7 - 11:4 - 11:1",
        "St": "4",
        "ES": "111878",
        "hash": "1a63fb9cbea65dee6da67dbcd2068e1b",
        "status": "0",
        "youtube_Id": "isHvWwL2naA",
        "createdAt": "2023-09-07 14:16:15",
        "player_1": "Diaryan Aleksandr",
        "player_1_url": "https://stats.sportgenerate.com/player/diaryan-aleksandr/",
        "player_2": "Soghomonyan Hrayr",
        "player_2_url": "https://stats.sportgenerate.com/player/soghomonyan-hrayr/"
    },
    {
        "id": "13913932",
        "date": "2023-09-08 10:10:00",
        "end_date": "2023-09-08 10:23:03",
        "tournament_id": "33714",
        "T1": "994",
        "T2": "989",
        "S1": "0",
        "S2": "3",
        "PS": "5:11 - 7:11 - 6:11 - 0:0 - 0:0",
        "St": "4",
        "ES": "0",
        "hash": "95f70007a0dc619325b54f5815c99169",
        "status": "0",
        "youtube_Id": "fm7JJWgXg_Q",
        "createdAt": "2023-09-07 14:15:16",
        "player_1": "Nazaryan Mushegh",
        "player_1_url": "https://stats.sportgenerate.com/player/nazaryan-mushegh/",
        "player_2": "Nikoghosyan Narek",
        "player_2_url": "https://stats.sportgenerate.com/player/nikoghosyan-narek/"
    }
]