[
    {
        "id": "16847543",
        "date": "2024-02-12 17:45:00",
        "end_date": "2024-02-12 18:03:40",
        "tournament_id": "33714",
        "T1": "2155",
        "T2": "1970",
        "S1": "1",
        "S2": "3",
        "PS": "13:11 - 9:11 - 9:11 - 6:11 - 0:0",
        "St": "4",
        "ES": "0",
        "hash": "a58f2536467ab79bc24451ada51ab2be",
        "status": "0",
        "youtube_Id": "ND3GgTZRYlY",
        "createdAt": "2024-02-11 13:11:27",
        "player_1": "Petrosyan Davit",
        "player_1_url": "https://stats.sportgenerate.com/player/petrosyan-davit/",
        "player_2": "Gevorgyan Hayk",
        "player_2_url": "https://stats.sportgenerate.com/player/gevorgyan-hayk/"
    },
    {
        "id": "16847542",
        "date": "2024-02-12 17:30:00",
        "end_date": "2024-02-12 17:47:15",
        "tournament_id": "33714",
        "T1": "988",
        "T2": "992",
        "S1": "3",
        "S2": "1",
        "PS": "11:8 - 11:8 - 9:11 - 11:9 - 0:0",
        "St": "4",
        "ES": "111878",
        "hash": "2edacce052639b02be0bfd9992f2e8ad",
        "status": "0",
        "youtube_Id": "UdpjaAXYgKc",
        "createdAt": "2024-02-11 13:11:27",
        "player_1": "Grigoryan Erik",
        "player_1_url": "https://stats.sportgenerate.com/player/grigoryan-erik/",
        "player_2": "Gevorgyan Gegham",
        "player_2_url": "https://stats.sportgenerate.com/player/gevorgyan-gegham/"
    },
    {
        "id": "16847529",
        "date": "2024-02-12 17:15:00",
        "end_date": "2024-02-12 17:26:28",
        "tournament_id": "33714",
        "T1": "2558",
        "T2": "2155",
        "S1": "3",
        "S2": "0",
        "PS": "11:4 - 11:4 - 11:7 - 0:0 - 0:0",
        "St": "4",
        "ES": "0",
        "hash": "7847a31efd408c18805b1df22e091b7b",
        "status": "0",
        "youtube_Id": "_0jwXs6yRL8",
        "createdAt": "2024-02-11 13:11:27",
        "player_1": "Arutyunov Ruben",
        "player_1_url": "https://stats.sportgenerate.com/player/arutyunov-ruben/",
        "player_2": "Petrosyan Davit",
        "player_2_url": "https://stats.sportgenerate.com/player/petrosyan-davit/"
    },
    {
        "id": "16847526",
        "date": "2024-02-12 17:00:00",
        "end_date": "2024-02-12 17:12:48",
        "tournament_id": "33714",
        "T1": "988",
        "T2": "1970",
        "S1": "0",
        "S2": "3",
        "PS": "10:12 - 6:11 - 6:11 - 0:0 - 0:0",
        "St": "4",
        "ES": "111878",
        "hash": "60e8546cceba48aa12adf06e7ad77b84",
        "status": "0",
        "youtube_Id": "Vn7KeAWAsQk",
        "createdAt": "2024-02-11 13:10:27",
        "player_1": "Grigoryan Erik",
        "player_1_url": "https://stats.sportgenerate.com/player/grigoryan-erik/",
        "player_2": "Gevorgyan Hayk",
        "player_2_url": "https://stats.sportgenerate.com/player/gevorgyan-hayk/"
    },
    {
        "id": "16847524",
        "date": "2024-02-12 16:45:00",
        "end_date": "2024-02-12 16:55:24",
        "tournament_id": "33714",
        "T1": "992",
        "T2": "2558",
        "S1": "0",
        "S2": "3",
        "PS": "5:11 - 3:11 - 3:11 - 0:0 - 0:0",
        "St": "4",
        "ES": "0",
        "hash": "adfcbb99f113d6e6b0ab5f596d665b7b",
        "status": "0",
        "youtube_Id": "iLsC8ZKs0Ek",
        "createdAt": "2024-02-11 13:10:27",
        "player_1": "Gevorgyan Gegham",
        "player_1_url": "https://stats.sportgenerate.com/player/gevorgyan-gegham/",
        "player_2": "Arutyunov Ruben",
        "player_2_url": "https://stats.sportgenerate.com/player/arutyunov-ruben/"
    },
    {
        "id": "16847522",
        "date": "2024-02-12 16:30:00",
        "end_date": "2024-02-12 16:44:52",
        "tournament_id": "33714",
        "T1": "2155",
        "T2": "988",
        "S1": "0",
        "S2": "3",
        "PS": "8:11 - 8:11 - 9:11 - 0:0 - 0:0",
        "St": "4",
        "ES": "111878",
        "hash": "74e2370fcd15c27f831942ccfc702773",
        "status": "0",
        "youtube_Id": "n7sSpDN9c_4",
        "createdAt": "2024-02-11 13:10:27",
        "player_1": "Petrosyan Davit",
        "player_1_url": "https://stats.sportgenerate.com/player/petrosyan-davit/",
        "player_2": "Grigoryan Erik",
        "player_2_url": "https://stats.sportgenerate.com/player/grigoryan-erik/"
    },
    {
        "id": "16847519",
        "date": "2024-02-12 16:15:00",
        "end_date": "2024-02-12 16:31:30",
        "tournament_id": "33714",
        "T1": "1970",
        "T2": "2558",
        "S1": "0",
        "S2": "3",
        "PS": "7:11 - 10:12 - 9:11 - 0:0 - 0:0",
        "St": "4",
        "ES": "0",
        "hash": "f0f40d0aae871a2cfafc84bb9c12fe9c",
        "status": "0",
        "youtube_Id": "oUCttY2huro",
        "createdAt": "2024-02-11 13:10:27",
        "player_1": "Gevorgyan Hayk",
        "player_1_url": "https://stats.sportgenerate.com/player/gevorgyan-hayk/",
        "player_2": "Arutyunov Ruben",
        "player_2_url": "https://stats.sportgenerate.com/player/arutyunov-ruben/"
    },
    {
        "id": "16847518",
        "date": "2024-02-12 16:00:00",
        "end_date": "2024-02-12 16:13:49",
        "tournament_id": "33714",
        "T1": "992",
        "T2": "2155",
        "S1": "0",
        "S2": "3",
        "PS": "7:11 - 8:11 - 4:11 - 0:0 - 0:0",
        "St": "4",
        "ES": "111878",
        "hash": "034b0f95b088c9b45309420509fba190",
        "status": "0",
        "youtube_Id": "NprquJwuCe0",
        "createdAt": "2024-02-11 13:10:27",
        "player_1": "Gevorgyan Gegham",
        "player_1_url": "https://stats.sportgenerate.com/player/gevorgyan-gegham/",
        "player_2": "Petrosyan Davit",
        "player_2_url": "https://stats.sportgenerate.com/player/petrosyan-davit/"
    },
    {
        "id": "16847516",
        "date": "2024-02-12 15:45:00",
        "end_date": "2024-02-12 15:54:17",
        "tournament_id": "33714",
        "T1": "2558",
        "T2": "988",
        "S1": "3",
        "S2": "0",
        "PS": "11:5 - 11:1 - 11:2 - 0:0 - 0:0",
        "St": "4",
        "ES": "0",
        "hash": "94df326b6005390d3f701b07a69de4d2",
        "status": "0",
        "youtube_Id": "qlvZqp-TfMM",
        "createdAt": "2024-02-11 13:09:27",
        "player_1": "Arutyunov Ruben",
        "player_1_url": "https://stats.sportgenerate.com/player/arutyunov-ruben/",
        "player_2": "Grigoryan Erik",
        "player_2_url": "https://stats.sportgenerate.com/player/grigoryan-erik/"
    },
    {
        "id": "16847514",
        "date": "2024-02-12 15:30:00",
        "end_date": "2024-02-12 15:49:16",
        "tournament_id": "33714",
        "T1": "1970",
        "T2": "992",
        "S1": "3",
        "S2": "1",
        "PS": "9:11 - 11:9 - 11:2 - 11:7 - 0:0",
        "St": "4",
        "ES": "111878",
        "hash": "be2513b67d92237e7256db25b98a49e9",
        "status": "0",
        "youtube_Id": "NXlRQBqGvy4",
        "createdAt": "2024-02-11 13:09:27",
        "player_1": "Gevorgyan Hayk",
        "player_1_url": "https://stats.sportgenerate.com/player/gevorgyan-hayk/",
        "player_2": "Gevorgyan Gegham",
        "player_2_url": "https://stats.sportgenerate.com/player/gevorgyan-gegham/"
    },
    {
        "id": "16847512",
        "date": "2024-02-12 15:20:00",
        "end_date": "2024-02-12 15:30:23",
        "tournament_id": "33714",
        "T1": "1365",
        "T2": "995",
        "S1": "0",
        "S2": "3",
        "PS": "7:11 - 9:11 - 7:11 - 0:0 - 0:0",
        "St": "4",
        "ES": "0",
        "hash": "c0dfa85c807209ae169df19a9c5ff9fd",
        "status": "0",
        "youtube_Id": "R__mHMbr7Qo",
        "createdAt": "2024-02-11 13:09:27",
        "player_1": "Soghomonyan Hrayr",
        "player_1_url": "https://stats.sportgenerate.com/player/soghomonyan-hrayr/",
        "player_2": "Papyan Karen",
        "player_2_url": "https://stats.sportgenerate.com/player/papyan-karen/"
    },
    {
        "id": "16847508",
        "date": "2024-02-12 15:05:00",
        "end_date": "2024-02-12 15:28:28",
        "tournament_id": "33714",
        "T1": "986",
        "T2": "2497",
        "S1": "2",
        "S2": "3",
        "PS": "11:9 - 6:11 - 11:4 - 11:13 - 5:11",
        "St": "4",
        "ES": "111878",
        "hash": "b1d03c43fc83ea1c75298745a288e5ea",
        "status": "0",
        "youtube_Id": "FJ8djO3ysv4",
        "createdAt": "2024-02-11 13:09:27",
        "player_1": "Mkrtchyan Andranik",
        "player_1_url": "https://stats.sportgenerate.com/player/mkrtchyan-andranik/",
        "player_2": "Rafayelyan Edgar",
        "player_2_url": "https://stats.sportgenerate.com/player/rafayelyan-edgar/"
    },
    {
        "id": "16847507",
        "date": "2024-02-12 14:55:00",
        "end_date": "2024-02-12 15:09:33",
        "tournament_id": "33714",
        "T1": "991",
        "T2": "1365",
        "S1": "3",
        "S2": "1",
        "PS": "11:5 - 11:4 - 5:11 - 11:7 - 0:0",
        "St": "4",
        "ES": "111878",
        "hash": "b207d9c531787668a967e4397010dfef",
        "status": "0",
        "youtube_Id": "jtAZJACek54",
        "createdAt": "2024-02-11 13:09:27",
        "player_1": "Diaryan Aleksandr",
        "player_1_url": "https://stats.sportgenerate.com/player/diaryan-aleksandr/",
        "player_2": "Soghomonyan Hrayr",
        "player_2_url": "https://stats.sportgenerate.com/player/soghomonyan-hrayr/"
    },
    {
        "id": "16847502",
        "date": "2024-02-12 14:35:00",
        "end_date": "2024-02-12 14:55:52",
        "tournament_id": "33714",
        "T1": "995",
        "T2": "986",
        "S1": "3",
        "S2": "2",
        "PS": "6:11 - 8:11 - 11:8 - 11:8 - 11:9",
        "St": "4",
        "ES": "111878",
        "hash": "a0e8622df8befbe42c0545103d52b02b",
        "status": "0",
        "youtube_Id": "TvBGNBZBJ-w",
        "createdAt": "2024-02-11 13:08:27",
        "player_1": "Papyan Karen",
        "player_1_url": "https://stats.sportgenerate.com/player/papyan-karen/",
        "player_2": "Mkrtchyan Andranik",
        "player_2_url": "https://stats.sportgenerate.com/player/mkrtchyan-andranik/"
    },
    {
        "id": "16847493",
        "date": "2024-02-12 14:15:00",
        "end_date": "2024-02-12 14:46:50",
        "tournament_id": "33714",
        "T1": "991",
        "T2": "2497",
        "S1": "3",
        "S2": "2",
        "PS": "11:8 - 9:11 - 11:8 - 11:13 - 14:12",
        "St": "4",
        "ES": "0",
        "hash": "18cfa7567dea9738c70c8889528e1e9e",
        "status": "0",
        "youtube_Id": "jsquIpyRMlw",
        "createdAt": "2024-02-11 13:08:27",
        "player_1": "Diaryan Aleksandr",
        "player_1_url": "https://stats.sportgenerate.com/player/diaryan-aleksandr/",
        "player_2": "Rafayelyan Edgar",
        "player_2_url": "https://stats.sportgenerate.com/player/rafayelyan-edgar/"
    },
    {
        "id": "16847491",
        "date": "2024-02-12 14:00:00",
        "end_date": "2024-02-12 14:19:33",
        "tournament_id": "33714",
        "T1": "1365",
        "T2": "986",
        "S1": "3",
        "S2": "1",
        "PS": "5:11 - 11:4 - 11:7 - 12:10 - 0:0",
        "St": "4",
        "ES": "111878",
        "hash": "da354f86a4223bc7922e322475f61acf",
        "status": "0",
        "youtube_Id": "IsEgCGQSwGs",
        "createdAt": "2024-02-11 13:08:27",
        "player_1": "Soghomonyan Hrayr",
        "player_1_url": "https://stats.sportgenerate.com/player/soghomonyan-hrayr/",
        "player_2": "Mkrtchyan Andranik",
        "player_2_url": "https://stats.sportgenerate.com/player/mkrtchyan-andranik/"
    },
    {
        "id": "16847488",
        "date": "2024-02-12 13:45:00",
        "end_date": "2024-02-12 14:06:55",
        "tournament_id": "33714",
        "T1": "995",
        "T2": "991",
        "S1": "3",
        "S2": "1",
        "PS": "11:8 - 7:11 - 11:9 - 17:15 - 0:0",
        "St": "4",
        "ES": "0",
        "hash": "844533b266a63af057eee827c06489dd",
        "status": "0",
        "youtube_Id": "IGqAhmsBOFc",
        "createdAt": "2024-02-11 13:08:27",
        "player_1": "Papyan Karen",
        "player_1_url": "https://stats.sportgenerate.com/player/papyan-karen/",
        "player_2": "Diaryan Aleksandr",
        "player_2_url": "https://stats.sportgenerate.com/player/diaryan-aleksandr/"
    },
    {
        "id": "16847485",
        "date": "2024-02-12 13:30:00",
        "end_date": "2024-02-12 13:48:32",
        "tournament_id": "33714",
        "T1": "2497",
        "T2": "1365",
        "S1": "3",
        "S2": "1",
        "PS": "11:5 - 15:17 - 11:7 - 11:8 - 0:0",
        "St": "4",
        "ES": "111878",
        "hash": "5aa32a883a6c2f49f376a2704f2ca367",
        "status": "0",
        "youtube_Id": "rEA12zm3IA0",
        "createdAt": "2024-02-11 13:07:27",
        "player_1": "Rafayelyan Edgar",
        "player_1_url": "https://stats.sportgenerate.com/player/rafayelyan-edgar/",
        "player_2": "Soghomonyan Hrayr",
        "player_2_url": "https://stats.sportgenerate.com/player/soghomonyan-hrayr/"
    },
    {
        "id": "16847483",
        "date": "2024-02-12 13:15:00",
        "end_date": "2024-02-12 13:26:34",
        "tournament_id": "33714",
        "T1": "986",
        "T2": "991",
        "S1": "0",
        "S2": "3",
        "PS": "3:11 - 5:11 - 7:11 - 0:0 - 0:0",
        "St": "4",
        "ES": "0",
        "hash": "a2281ad75f01da812d85dc616f1348d2",
        "status": "0",
        "youtube_Id": "uHQve-qW-hs",
        "createdAt": "2024-02-11 13:07:27",
        "player_1": "Mkrtchyan Andranik",
        "player_1_url": "https://stats.sportgenerate.com/player/mkrtchyan-andranik/",
        "player_2": "Diaryan Aleksandr",
        "player_2_url": "https://stats.sportgenerate.com/player/diaryan-aleksandr/"
    },
    {
        "id": "16847481",
        "date": "2024-02-12 13:00:00",
        "end_date": "2024-02-12 13:17:05",
        "tournament_id": "33714",
        "T1": "2497",
        "T2": "995",
        "S1": "1",
        "S2": "3",
        "PS": "5:11 - 8:11 - 11:5 - 8:11 - 0:0",
        "St": "4",
        "ES": "111878",
        "hash": "27901b1283ebde3344bd82997ce4b58b",
        "status": "0",
        "youtube_Id": "MRV8hQIjdd4",
        "createdAt": "2024-02-11 13:07:27",
        "player_1": "Rafayelyan Edgar",
        "player_1_url": "https://stats.sportgenerate.com/player/rafayelyan-edgar/",
        "player_2": "Papyan Karen",
        "player_2_url": "https://stats.sportgenerate.com/player/papyan-karen/"
    },
    {
        "id": "16847477",
        "date": "2024-02-12 12:15:00",
        "end_date": "2024-02-12 12:26:56",
        "tournament_id": "33714",
        "T1": "1365",
        "T2": "991",
        "S1": "0",
        "S2": "3",
        "PS": "10:12 - 3:11 - 7:11 - 0:0 - 0:0",
        "St": "4",
        "ES": "0",
        "hash": "02819d0bd6f6c44fb92a3942639aa7fc",
        "status": "0",
        "youtube_Id": "hqU341DLM4U",
        "createdAt": "2024-02-11 13:07:27",
        "player_1": "Soghomonyan Hrayr",
        "player_1_url": "https://stats.sportgenerate.com/player/soghomonyan-hrayr/",
        "player_2": "Diaryan Aleksandr",
        "player_2_url": "https://stats.sportgenerate.com/player/diaryan-aleksandr/"
    },
    {
        "id": "16847471",
        "date": "2024-02-12 12:00:00",
        "end_date": "2024-02-12 12:11:15",
        "tournament_id": "33714",
        "T1": "2497",
        "T2": "986",
        "S1": "3",
        "S2": "0",
        "PS": "11:0 - 11:8 - 11:6 - 0:0 - 0:0",
        "St": "4",
        "ES": "111878",
        "hash": "6cf67ca0a93568a7b400f1ec97c3d757",
        "status": "0",
        "youtube_Id": "RW6I8EXFv6I",
        "createdAt": "2024-02-11 13:07:27",
        "player_1": "Rafayelyan Edgar",
        "player_1_url": "https://stats.sportgenerate.com/player/rafayelyan-edgar/",
        "player_2": "Mkrtchyan Andranik",
        "player_2_url": "https://stats.sportgenerate.com/player/mkrtchyan-andranik/"
    },
    {
        "id": "16847463",
        "date": "2024-02-12 11:45:00",
        "end_date": "2024-02-12 12:01:40",
        "tournament_id": "33714",
        "T1": "995",
        "T2": "1365",
        "S1": "3",
        "S2": "1",
        "PS": "13:11 - 11:6 - 9:11 - 11:6 - 0:0",
        "St": "4",
        "ES": "0",
        "hash": "ae58fbee3627aa70f18effe878a7a1ad",
        "status": "0",
        "youtube_Id": "BQj4YodY_gQ",
        "createdAt": "2024-02-11 13:06:27",
        "player_1": "Papyan Karen",
        "player_1_url": "https://stats.sportgenerate.com/player/papyan-karen/",
        "player_2": "Soghomonyan Hrayr",
        "player_2_url": "https://stats.sportgenerate.com/player/soghomonyan-hrayr/"
    },
    {
        "id": "16847461",
        "date": "2024-02-12 11:30:00",
        "end_date": "2024-02-12 11:44:44",
        "tournament_id": "33714",
        "T1": "2497",
        "T2": "991",
        "S1": "0",
        "S2": "3",
        "PS": "4:11 - 6:11 - 8:11 - 0:0 - 0:0",
        "St": "4",
        "ES": "111878",
        "hash": "2356ab7edb63561aade333e66f0c545f",
        "status": "0",
        "youtube_Id": "GgIl54MHZ6M",
        "createdAt": "2024-02-11 13:06:27",
        "player_1": "Rafayelyan Edgar",
        "player_1_url": "https://stats.sportgenerate.com/player/rafayelyan-edgar/",
        "player_2": "Diaryan Aleksandr",
        "player_2_url": "https://stats.sportgenerate.com/player/diaryan-aleksandr/"
    },
    {
        "id": "16847459",
        "date": "2024-02-12 11:15:00",
        "end_date": "2024-02-12 11:27:46",
        "tournament_id": "33714",
        "T1": "986",
        "T2": "995",
        "S1": "0",
        "S2": "3",
        "PS": "10:12 - 7:11 - 7:11 - 0:0 - 0:0",
        "St": "4",
        "ES": "0",
        "hash": "a8678dab111b2be38c261125757a567d",
        "status": "0",
        "youtube_Id": "roSgimV5Y_k",
        "createdAt": "2024-02-11 13:06:27",
        "player_1": "Mkrtchyan Andranik",
        "player_1_url": "https://stats.sportgenerate.com/player/mkrtchyan-andranik/",
        "player_2": "Papyan Karen",
        "player_2_url": "https://stats.sportgenerate.com/player/papyan-karen/"
    },
    {
        "id": "16847458",
        "date": "2024-02-12 11:00:00",
        "end_date": "2024-02-12 11:12:18",
        "tournament_id": "33714",
        "T1": "1365",
        "T2": "2497",
        "S1": "0",
        "S2": "3",
        "PS": "5:11 - 7:11 - 11:13 - 0:0 - 0:0",
        "St": "4",
        "ES": "111878",
        "hash": "f8a81add9cb6db7ed3c487df6dc9d87f",
        "status": "0",
        "youtube_Id": "Yu2ku4gun3A",
        "createdAt": "2024-02-11 13:06:27",
        "player_1": "Soghomonyan Hrayr",
        "player_1_url": "https://stats.sportgenerate.com/player/soghomonyan-hrayr/",
        "player_2": "Rafayelyan Edgar",
        "player_2_url": "https://stats.sportgenerate.com/player/rafayelyan-edgar/"
    },
    {
        "id": "16847457",
        "date": "2024-02-12 10:45:00",
        "end_date": "2024-02-12 11:08:06",
        "tournament_id": "33714",
        "T1": "991",
        "T2": "995",
        "S1": "3",
        "S2": "2",
        "PS": "7:11 - 11:6 - 11:8 - 8:11 - 11:3",
        "St": "4",
        "ES": "0",
        "hash": "e7e666ebca68ef93bbfc686705a0c28d",
        "status": "0",
        "youtube_Id": "ItX_Mrol5VU",
        "createdAt": "2024-02-11 13:06:27",
        "player_1": "Diaryan Aleksandr",
        "player_1_url": "https://stats.sportgenerate.com/player/diaryan-aleksandr/",
        "player_2": "Papyan Karen",
        "player_2_url": "https://stats.sportgenerate.com/player/papyan-karen/"
    },
    {
        "id": "16847455",
        "date": "2024-02-12 10:30:00",
        "end_date": "2024-02-12 10:53:13",
        "tournament_id": "33714",
        "T1": "986",
        "T2": "1365",
        "S1": "1",
        "S2": "3",
        "PS": "11:7 - 9:11 - 13:15 - 9:11 - 0:0",
        "St": "4",
        "ES": "111878",
        "hash": "d545c8de077ac92e5918e8a522dd8266",
        "status": "0",
        "youtube_Id": "q2qaWLa8Wi8",
        "createdAt": "2024-02-11 13:05:26",
        "player_1": "Mkrtchyan Andranik",
        "player_1_url": "https://stats.sportgenerate.com/player/mkrtchyan-andranik/",
        "player_2": "Soghomonyan Hrayr",
        "player_2_url": "https://stats.sportgenerate.com/player/soghomonyan-hrayr/"
    },
    {
        "id": "16847453",
        "date": "2024-02-12 10:15:00",
        "end_date": "2024-02-12 10:26:59",
        "tournament_id": "33714",
        "T1": "995",
        "T2": "2497",
        "S1": "0",
        "S2": "3",
        "PS": "4:11 - 9:11 - 3:11 - 0:0 - 0:0",
        "St": "4",
        "ES": "0",
        "hash": "9e3462509a4f2e498c65ab555c4464d7",
        "status": "0",
        "youtube_Id": "ltQeeKFyofo",
        "createdAt": "2024-02-11 13:05:26",
        "player_1": "Papyan Karen",
        "player_1_url": "https://stats.sportgenerate.com/player/papyan-karen/",
        "player_2": "Rafayelyan Edgar",
        "player_2_url": "https://stats.sportgenerate.com/player/rafayelyan-edgar/"
    },
    {
        "id": "16847447",
        "date": "2024-02-12 10:00:00",
        "end_date": "2024-02-12 10:16:25",
        "tournament_id": "33714",
        "T1": "991",
        "T2": "986",
        "S1": "3",
        "S2": "1",
        "PS": "11:6 - 9:11 - 11:9 - 11:3 - 0:0",
        "St": "4",
        "ES": "111878",
        "hash": "65087c2129607bb6aedafbb1fa190db3",
        "status": "0",
        "youtube_Id": "P4eet1trfgo",
        "createdAt": "2024-02-11 13:05:26",
        "player_1": "Diaryan Aleksandr",
        "player_1_url": "https://stats.sportgenerate.com/player/diaryan-aleksandr/",
        "player_2": "Mkrtchyan Andranik",
        "player_2_url": "https://stats.sportgenerate.com/player/mkrtchyan-andranik/"
    }
]