[
    {
        "id": "17673800",
        "date": "2024-03-24 17:45:00",
        "end_date": "2024-03-24 17:59:25",
        "tournament_id": "33714",
        "T1": "992",
        "T2": "1365",
        "S1": "0",
        "S2": "3",
        "PS": "6:11 - 4:11 - 9:11 - 0:0 - 0:0",
        "St": "4",
        "ES": "0",
        "hash": "7e56c4a8ac7fe9fe6b61fdc98ba5b7a4",
        "status": "0",
        "youtube_Id": "6Ar9INFibcM",
        "createdAt": "2024-03-23 16:15:32",
        "player_1": "Gevorgyan Gegham",
        "player_1_url": "https://stats.sportgenerate.com/player/gevorgyan-gegham/",
        "player_2": "Soghomonyan Hrayr",
        "player_2_url": "https://stats.sportgenerate.com/player/soghomonyan-hrayr/"
    },
    {
        "id": "17673797",
        "date": "2024-03-24 17:35:00",
        "end_date": "2024-03-24 17:46:22",
        "tournament_id": "33714",
        "T1": "986",
        "T2": "2155",
        "S1": "3",
        "S2": "0",
        "PS": "11:9 - 11:4 - 11:5 - 0:0 - 0:0",
        "St": "4",
        "ES": "0",
        "hash": "e3bd7edcf1b8fafa2626e710f6eedd89",
        "status": "0",
        "youtube_Id": "zpmLVu82CR0",
        "createdAt": "2024-03-23 16:15:32",
        "player_1": "Mkrtchyan Andranik",
        "player_1_url": "https://stats.sportgenerate.com/player/mkrtchyan-andranik/",
        "player_2": "Petrosyan Davit",
        "player_2_url": "https://stats.sportgenerate.com/player/petrosyan-davit/"
    },
    {
        "id": "17673794",
        "date": "2024-03-24 17:15:00",
        "end_date": "2024-03-24 17:25:47",
        "tournament_id": "33714",
        "T1": "1970",
        "T2": "992",
        "S1": "3",
        "S2": "0",
        "PS": "11:4 - 11:2 - 11:6 - 0:0 - 0:0",
        "St": "4",
        "ES": "111878",
        "hash": "948bcbc149348c28a1c2b9d91fa44f53",
        "status": "0",
        "youtube_Id": "OZwhWtS5YEU",
        "createdAt": "2024-03-23 16:15:32",
        "player_1": "Gevorgyan Hayk",
        "player_1_url": "https://stats.sportgenerate.com/player/gevorgyan-hayk/",
        "player_2": "Gevorgyan Gegham",
        "player_2_url": "https://stats.sportgenerate.com/player/gevorgyan-gegham/"
    },
    {
        "id": "17673783",
        "date": "2024-03-24 17:00:00",
        "end_date": "2024-03-24 17:19:38",
        "tournament_id": "33714",
        "T1": "986",
        "T2": "1365",
        "S1": "1",
        "S2": "3",
        "PS": "7:11 - 8:11 - 11:8 - 4:11 - 0:0",
        "St": "4",
        "ES": "0",
        "hash": "97e19cbd7ab9a9cf5018f27f987d3f54",
        "status": "0",
        "youtube_Id": "daOznDHijJs",
        "createdAt": "2024-03-23 16:14:30",
        "player_1": "Mkrtchyan Andranik",
        "player_1_url": "https://stats.sportgenerate.com/player/mkrtchyan-andranik/",
        "player_2": "Soghomonyan Hrayr",
        "player_2_url": "https://stats.sportgenerate.com/player/soghomonyan-hrayr/"
    },
    {
        "id": "17673756",
        "date": "2024-03-24 16:45:00",
        "end_date": "2024-03-24 16:56:07",
        "tournament_id": "33714",
        "T1": "2155",
        "T2": "1970",
        "S1": "0",
        "S2": "3",
        "PS": "7:11 - 4:11 - 9:11 - 0:0 - 0:0",
        "St": "4",
        "ES": "0",
        "hash": "8684370a8c3caf3a5aabcc349674f773",
        "status": "0",
        "youtube_Id": "Jms_xu_wR28",
        "createdAt": "2024-03-23 16:14:30",
        "player_1": "Petrosyan Davit",
        "player_1_url": "https://stats.sportgenerate.com/player/petrosyan-davit/",
        "player_2": "Gevorgyan Hayk",
        "player_2_url": "https://stats.sportgenerate.com/player/gevorgyan-hayk/"
    },
    {
        "id": "17673753",
        "date": "2024-03-24 16:30:00",
        "end_date": "2024-03-24 16:49:40",
        "tournament_id": "33714",
        "T1": "992",
        "T2": "986",
        "S1": "1",
        "S2": "3",
        "PS": "9:11 - 11:7 - 11:13 - 6:11 - 0:0",
        "St": "4",
        "ES": "111878",
        "hash": "4d3c4cf010ad0ad9016ff88fae9b7307",
        "status": "0",
        "youtube_Id": "SwRZLLXZtUI",
        "createdAt": "2024-03-23 16:14:30",
        "player_1": "Gevorgyan Gegham",
        "player_1_url": "https://stats.sportgenerate.com/player/gevorgyan-gegham/",
        "player_2": "Mkrtchyan Andranik",
        "player_2_url": "https://stats.sportgenerate.com/player/mkrtchyan-andranik/"
    },
    {
        "id": "17673751",
        "date": "2024-03-24 16:15:00",
        "end_date": "2024-03-24 16:31:47",
        "tournament_id": "33714",
        "T1": "1365",
        "T2": "1970",
        "S1": "3",
        "S2": "1",
        "PS": "6:11 - 11:9 - 11:4 - 12:10 - 0:0",
        "St": "4",
        "ES": "0",
        "hash": "e021046b64fdc2bb60c8a8e99e093afe",
        "status": "0",
        "youtube_Id": "FHigezSvggY",
        "createdAt": "2024-03-23 16:14:30",
        "player_1": "Soghomonyan Hrayr",
        "player_1_url": "https://stats.sportgenerate.com/player/soghomonyan-hrayr/",
        "player_2": "Gevorgyan Hayk",
        "player_2_url": "https://stats.sportgenerate.com/player/gevorgyan-hayk/"
    },
    {
        "id": "17673746",
        "date": "2024-03-24 16:05:00",
        "end_date": "2024-03-24 16:20:24",
        "tournament_id": "33714",
        "T1": "2155",
        "T2": "992",
        "S1": "3",
        "S2": "0",
        "PS": "11:7 - 11:9 - 11:7 - 0:0 - 0:0",
        "St": "4",
        "ES": "0",
        "hash": "2ec858c32f61f5a1dc848f46393a89a3",
        "status": "0",
        "youtube_Id": "sgkTo03HxWg",
        "createdAt": "2024-03-23 16:13:31",
        "player_1": "Petrosyan Davit",
        "player_1_url": "https://stats.sportgenerate.com/player/petrosyan-davit/",
        "player_2": "Gevorgyan Gegham",
        "player_2_url": "https://stats.sportgenerate.com/player/gevorgyan-gegham/"
    },
    {
        "id": "17673733",
        "date": "2024-03-24 15:45:00",
        "end_date": "2024-03-24 16:04:21",
        "tournament_id": "33714",
        "T1": "1970",
        "T2": "986",
        "S1": "1",
        "S2": "3",
        "PS": "14:12 - 4:11 - 8:11 - 9:11 - 0:0",
        "St": "4",
        "ES": "111878",
        "hash": "14d8c22e5a0e8a2f18de5cea7b839ec1",
        "status": "0",
        "youtube_Id": "bS2wpAE8Eus",
        "createdAt": "2024-03-23 16:13:31",
        "player_1": "Gevorgyan Hayk",
        "player_1_url": "https://stats.sportgenerate.com/player/gevorgyan-hayk/",
        "player_2": "Mkrtchyan Andranik",
        "player_2_url": "https://stats.sportgenerate.com/player/mkrtchyan-andranik/"
    },
    {
        "id": "17673729",
        "date": "2024-03-24 15:40:00",
        "end_date": "2024-03-24 15:56:05",
        "tournament_id": "33714",
        "T1": "1365",
        "T2": "2155",
        "S1": "3",
        "S2": "0",
        "PS": "11:7 - 13:11 - 11:7 - 0:0 - 0:0",
        "St": "4",
        "ES": "0",
        "hash": "85abfcd29f1a218999545024bef2f68b",
        "status": "0",
        "youtube_Id": "9J9X1zIviFc",
        "createdAt": "2024-03-23 16:13:31",
        "player_1": "Soghomonyan Hrayr",
        "player_1_url": "https://stats.sportgenerate.com/player/soghomonyan-hrayr/",
        "player_2": "Petrosyan Davit",
        "player_2_url": "https://stats.sportgenerate.com/player/petrosyan-davit/"
    },
    {
        "id": "17673728",
        "date": "2024-03-24 15:20:00",
        "end_date": "2024-03-24 15:41:32",
        "tournament_id": "33714",
        "T1": "3905",
        "T2": "989",
        "S1": "3",
        "S2": "1",
        "PS": "8:11 - 13:11 - 11:8 - 11:5 - 0:0",
        "St": "4",
        "ES": "0",
        "hash": "8a194a6e0d3af993086c065a893edaa9",
        "status": "0",
        "youtube_Id": "_Ln18zpp3UQ",
        "createdAt": "2024-03-23 16:13:31",
        "player_1": "Hovhannesyan Rafik",
        "player_1_url": "https://stats.sportgenerate.com/player/hovhannesyan-rafik/",
        "player_2": "Nikoghosyan Narek",
        "player_2_url": "https://stats.sportgenerate.com/player/nikoghosyan-narek/"
    },
    {
        "id": "17673727",
        "date": "2024-03-24 15:20:00",
        "end_date": "2024-03-24 15:33:39",
        "tournament_id": "33714",
        "T1": "991",
        "T2": "994",
        "S1": "3",
        "S2": "0",
        "PS": "11:7 - 11:9 - 11:5 - 0:0 - 0:0",
        "St": "4",
        "ES": "111878",
        "hash": "af3ff276af3f183fc4b22c1a5afa0573",
        "status": "0",
        "youtube_Id": "xxxL3AHW1BE",
        "createdAt": "2024-03-23 16:12:30",
        "player_1": "Diaryan Aleksandr",
        "player_1_url": "https://stats.sportgenerate.com/player/diaryan-aleksandr/",
        "player_2": "Nazaryan Mushegh",
        "player_2_url": "https://stats.sportgenerate.com/player/nazaryan-mushegh/"
    },
    {
        "id": "17673725",
        "date": "2024-03-24 14:45:00",
        "end_date": "2024-03-24 15:05:35",
        "tournament_id": "33714",
        "T1": "3937",
        "T2": "3905",
        "S1": "3",
        "S2": "1",
        "PS": "9:11 - 11:6 - 11:7 - 11:5 - 0:0",
        "St": "4",
        "ES": "0",
        "hash": "67438fc0d8351267b11be0dcdf5d055c",
        "status": "0",
        "youtube_Id": "3pPLL3tBKH0",
        "createdAt": "2024-03-23 16:12:30",
        "player_1": "Asatryan Murad",
        "player_1_url": "https://stats.sportgenerate.com/player/asatryan-murad/",
        "player_2": "Hovhannesyan Rafik",
        "player_2_url": "https://stats.sportgenerate.com/player/hovhannesyan-rafik/"
    },
    {
        "id": "17673714",
        "date": "2024-03-24 14:30:00",
        "end_date": "2024-03-24 15:03:30",
        "tournament_id": "33714",
        "T1": "989",
        "T2": "991",
        "S1": "2",
        "S2": "3",
        "PS": "8:11 - 12:14 - 11:9 - 11:7 - 5:11",
        "St": "4",
        "ES": "0",
        "hash": "c88672a0f0bc666e3d825f16287a363f",
        "status": "0",
        "youtube_Id": null,
        "createdAt": "2024-03-23 16:12:30",
        "player_1": "Nikoghosyan Narek",
        "player_1_url": "https://stats.sportgenerate.com/player/nikoghosyan-narek/",
        "player_2": "Diaryan Aleksandr",
        "player_2_url": "https://stats.sportgenerate.com/player/diaryan-aleksandr/"
    },
    {
        "id": "17673712",
        "date": "2024-03-24 14:15:00",
        "end_date": "2024-03-24 14:32:41",
        "tournament_id": "33714",
        "T1": "3937",
        "T2": "994",
        "S1": "3",
        "S2": "1",
        "PS": "11:6 - 11:8 - 10:12 - 11:4 - 0:0",
        "St": "4",
        "ES": "0",
        "hash": "81979ef146ade74af7886a6443f0b85b",
        "status": "0",
        "youtube_Id": "bpmt-Xsde3w",
        "createdAt": "2024-03-23 16:12:30",
        "player_1": "Asatryan Murad",
        "player_1_url": "https://stats.sportgenerate.com/player/asatryan-murad/",
        "player_2": "Nazaryan Mushegh",
        "player_2_url": "https://stats.sportgenerate.com/player/nazaryan-mushegh/"
    },
    {
        "id": "17673696",
        "date": "2024-03-24 14:00:00",
        "end_date": "2024-03-24 14:20:44",
        "tournament_id": "33714",
        "T1": "3905",
        "T2": "991",
        "S1": "0",
        "S2": "3",
        "PS": "4:11 - 18:20 - 10:12 - 0:0 - 0:0",
        "St": "4",
        "ES": "0",
        "hash": "1e89e69d6ff206cb87922adb6bcd9a57",
        "status": "0",
        "youtube_Id": "IoHJaxDoh2s",
        "createdAt": "2024-03-23 16:11:30",
        "player_1": "Hovhannesyan Rafik",
        "player_1_url": "https://stats.sportgenerate.com/player/hovhannesyan-rafik/",
        "player_2": "Diaryan Aleksandr",
        "player_2_url": "https://stats.sportgenerate.com/player/diaryan-aleksandr/"
    },
    {
        "id": "17673693",
        "date": "2024-03-24 13:45:00",
        "end_date": "2024-03-24 14:06:14",
        "tournament_id": "33714",
        "T1": "989",
        "T2": "3937",
        "S1": "1",
        "S2": "3",
        "PS": "11:9 - 7:11 - 4:11 - 8:11 - 0:0",
        "St": "4",
        "ES": "0",
        "hash": "da0591399e3e63b8592dc549357722c9",
        "status": "0",
        "youtube_Id": "_eOixLfsYEQ",
        "createdAt": "2024-03-23 16:10:30",
        "player_1": "Nikoghosyan Narek",
        "player_1_url": "https://stats.sportgenerate.com/player/nikoghosyan-narek/",
        "player_2": "Asatryan Murad",
        "player_2_url": "https://stats.sportgenerate.com/player/asatryan-murad/"
    },
    {
        "id": "17673688",
        "date": "2024-03-24 13:30:00",
        "end_date": "2024-03-24 13:43:18",
        "tournament_id": "33714",
        "T1": "994",
        "T2": "3905",
        "S1": "3",
        "S2": "0",
        "PS": "11:8 - 11:9 - 12:10 - 0:0 - 0:0",
        "St": "4",
        "ES": "111878",
        "hash": "baec62f43e5df0076f44b12195002137",
        "status": "0",
        "youtube_Id": "D5t2yZl4qM8",
        "createdAt": "2024-03-23 16:10:30",
        "player_1": "Nazaryan Mushegh",
        "player_1_url": "https://stats.sportgenerate.com/player/nazaryan-mushegh/",
        "player_2": "Hovhannesyan Rafik",
        "player_2_url": "https://stats.sportgenerate.com/player/hovhannesyan-rafik/"
    },
    {
        "id": "17673686",
        "date": "2024-03-24 13:15:00",
        "end_date": "2024-03-24 13:35:08",
        "tournament_id": "33714",
        "T1": "991",
        "T2": "3937",
        "S1": "1",
        "S2": "3",
        "PS": "11:9 - 4:11 - 7:11 - 8:11 - 0:0",
        "St": "4",
        "ES": "0",
        "hash": "14dc54cafed026e5973234e5f9711a96",
        "status": "0",
        "youtube_Id": "s1lOPlxsjgk",
        "createdAt": "2024-03-23 16:10:30",
        "player_1": "Diaryan Aleksandr",
        "player_1_url": "https://stats.sportgenerate.com/player/diaryan-aleksandr/",
        "player_2": "Asatryan Murad",
        "player_2_url": "https://stats.sportgenerate.com/player/asatryan-murad/"
    },
    {
        "id": "17673684",
        "date": "2024-03-24 13:00:00",
        "end_date": "2024-03-24 13:15:21",
        "tournament_id": "33714",
        "T1": "994",
        "T2": "989",
        "S1": "3",
        "S2": "0",
        "PS": "11:8 - 11:6 - 13:11 - 0:0 - 0:0",
        "St": "4",
        "ES": "0",
        "hash": "e54e3b0e4121c90635ef180fc088ca45",
        "status": "0",
        "youtube_Id": "A7TMhby8sZE",
        "createdAt": "2024-03-23 16:10:30",
        "player_1": "Nazaryan Mushegh",
        "player_1_url": "https://stats.sportgenerate.com/player/nazaryan-mushegh/",
        "player_2": "Nikoghosyan Narek",
        "player_2_url": "https://stats.sportgenerate.com/player/nikoghosyan-narek/"
    },
    {
        "id": "17673677",
        "date": "2024-03-24 12:25:00",
        "end_date": "2024-03-24 12:39:17",
        "tournament_id": "33714",
        "T1": "3905",
        "T2": "3937",
        "S1": "0",
        "S2": "3",
        "PS": "7:11 - 6:11 - 5:11 - 0:0 - 0:0",
        "St": "4",
        "ES": "111878",
        "hash": "af0ba738b7b561b3e437964d1300c06c",
        "status": "0",
        "youtube_Id": "90EqNSe06tE",
        "createdAt": "2024-03-23 16:09:31",
        "player_1": "Hovhannesyan Rafik",
        "player_1_url": "https://stats.sportgenerate.com/player/hovhannesyan-rafik/",
        "player_2": "Asatryan Murad",
        "player_2_url": "https://stats.sportgenerate.com/player/asatryan-murad/"
    },
    {
        "id": "17673664",
        "date": "2024-03-24 12:10:00",
        "end_date": "2024-03-24 12:24:17",
        "tournament_id": "33714",
        "T1": "989",
        "T2": "3905",
        "S1": "3",
        "S2": "0",
        "PS": "11:9 - 11:3 - 11:6 - 0:0 - 0:0",
        "St": "4",
        "ES": "0",
        "hash": "084e969e2efc46650fae720bb508fb98",
        "status": "0",
        "youtube_Id": "FyK_eZkvS08",
        "createdAt": "2024-03-23 16:09:31",
        "player_1": "Nikoghosyan Narek",
        "player_1_url": "https://stats.sportgenerate.com/player/nikoghosyan-narek/",
        "player_2": "Hovhannesyan Rafik",
        "player_2_url": "https://stats.sportgenerate.com/player/hovhannesyan-rafik/"
    },
    {
        "id": "17673665",
        "date": "2024-03-24 12:05:00",
        "end_date": "2024-03-24 12:24:48",
        "tournament_id": "33714",
        "T1": "994",
        "T2": "991",
        "S1": "1",
        "S2": "3",
        "PS": "5:11 - 8:11 - 11:9 - 7:11 - 0:0",
        "St": "4",
        "ES": "0",
        "hash": "469cf0bed5c53c2b964937619fcfccd5",
        "status": "0",
        "youtube_Id": "mBbHBrMCpag",
        "createdAt": "2024-03-23 16:09:31",
        "player_1": "Nazaryan Mushegh",
        "player_1_url": "https://stats.sportgenerate.com/player/nazaryan-mushegh/",
        "player_2": "Diaryan Aleksandr",
        "player_2_url": "https://stats.sportgenerate.com/player/diaryan-aleksandr/"
    },
    {
        "id": "17673660",
        "date": "2024-03-24 11:30:00",
        "end_date": "2024-03-24 11:43:48",
        "tournament_id": "33714",
        "T1": "994",
        "T2": "3937",
        "S1": "0",
        "S2": "3",
        "PS": "6:11 - 7:11 - 6:11 - 0:0 - 0:0",
        "St": "4",
        "ES": "111878",
        "hash": "13b310a6049c88c23fbee4e4de2abbbb",
        "status": "0",
        "youtube_Id": "lM2z3Ksqoms",
        "createdAt": "2024-03-23 16:09:31",
        "player_1": "Nazaryan Mushegh",
        "player_1_url": "https://stats.sportgenerate.com/player/nazaryan-mushegh/",
        "player_2": "Asatryan Murad",
        "player_2_url": "https://stats.sportgenerate.com/player/asatryan-murad/"
    },
    {
        "id": "17673659",
        "date": "2024-03-24 11:25:00",
        "end_date": "2024-03-24 12:01:56",
        "tournament_id": "33714",
        "T1": "991",
        "T2": "989",
        "S1": "2",
        "S2": "3",
        "PS": "12:10 - 9:11 - 10:12 - 13:11 - 10:12",
        "St": "4",
        "ES": "0",
        "hash": "c5eb0cdd18d33c877447383821df7194",
        "status": "0",
        "youtube_Id": "8jbtUXrV-p8",
        "createdAt": "2024-03-23 16:09:31",
        "player_1": "Diaryan Aleksandr",
        "player_1_url": "https://stats.sportgenerate.com/player/diaryan-aleksandr/",
        "player_2": "Nikoghosyan Narek",
        "player_2_url": "https://stats.sportgenerate.com/player/nikoghosyan-narek/"
    },
    {
        "id": "17673655",
        "date": "2024-03-24 11:00:00",
        "end_date": "2024-03-24 11:12:26",
        "tournament_id": "33714",
        "T1": "3905",
        "T2": "994",
        "S1": "0",
        "S2": "3",
        "PS": "7:11 - 9:11 - 6:11 - 0:0 - 0:0",
        "St": "4",
        "ES": "0",
        "hash": "18599de3fca635e2d350ee89b2d83cf5",
        "status": "0",
        "youtube_Id": "QeLdV7_61Dg",
        "createdAt": "2024-03-23 16:08:31",
        "player_1": "Hovhannesyan Rafik",
        "player_1_url": "https://stats.sportgenerate.com/player/hovhannesyan-rafik/",
        "player_2": "Nazaryan Mushegh",
        "player_2_url": "https://stats.sportgenerate.com/player/nazaryan-mushegh/"
    },
    {
        "id": "17673652",
        "date": "2024-03-24 10:45:00",
        "end_date": "2024-03-24 11:06:08",
        "tournament_id": "33714",
        "T1": "3937",
        "T2": "989",
        "S1": "3",
        "S2": "1",
        "PS": "11:7 - 4:11 - 11:7 - 11:4 - 0:0",
        "St": "4",
        "ES": "111878",
        "hash": "323c08e410fe497d010fc29db76f1f18",
        "status": "0",
        "youtube_Id": "PzUD_wy1AtM",
        "createdAt": "2024-03-23 16:08:31",
        "player_1": "Asatryan Murad",
        "player_1_url": "https://stats.sportgenerate.com/player/asatryan-murad/",
        "player_2": "Nikoghosyan Narek",
        "player_2_url": "https://stats.sportgenerate.com/player/nikoghosyan-narek/"
    },
    {
        "id": "17673645",
        "date": "2024-03-24 10:30:00",
        "end_date": "2024-03-24 10:43:32",
        "tournament_id": "33714",
        "T1": "991",
        "T2": "3905",
        "S1": "3",
        "S2": "0",
        "PS": "11:6 - 11:7 - 11:6 - 0:0 - 0:0",
        "St": "4",
        "ES": "0",
        "hash": "9d20c72252b26116f87b7bbe1fa60a0e",
        "status": "0",
        "youtube_Id": "zP845x93Ttg",
        "createdAt": "2024-03-23 16:08:31",
        "player_1": "Diaryan Aleksandr",
        "player_1_url": "https://stats.sportgenerate.com/player/diaryan-aleksandr/",
        "player_2": "Hovhannesyan Rafik",
        "player_2_url": "https://stats.sportgenerate.com/player/hovhannesyan-rafik/"
    },
    {
        "id": "17673636",
        "date": "2024-03-24 10:15:00",
        "end_date": "2024-03-24 10:35:41",
        "tournament_id": "33714",
        "T1": "989",
        "T2": "994",
        "S1": "1",
        "S2": "3",
        "PS": "7:11 - 5:11 - 11:8 - 7:11 - 0:0",
        "St": "4",
        "ES": "0",
        "hash": "234af5082e91f869b2ca7a3d1e9141e5",
        "status": "0",
        "youtube_Id": "PUfUm0RlYWU",
        "createdAt": "2024-03-23 16:08:31",
        "player_1": "Nikoghosyan Narek",
        "player_1_url": "https://stats.sportgenerate.com/player/nikoghosyan-narek/",
        "player_2": "Nazaryan Mushegh",
        "player_2_url": "https://stats.sportgenerate.com/player/nazaryan-mushegh/"
    },
    {
        "id": "17673632",
        "date": "2024-03-24 10:00:00",
        "end_date": "2024-03-24 10:17:37",
        "tournament_id": "33714",
        "T1": "3937",
        "T2": "991",
        "S1": "3",
        "S2": "0",
        "PS": "11:9 - 12:10 - 11:6 - 0:0 - 0:0",
        "St": "4",
        "ES": "111878",
        "hash": "a11fe8b8ce09ade554ba73d3ddb5e17c",
        "status": "0",
        "youtube_Id": "rbouIqXrhXY",
        "createdAt": "2024-03-23 16:08:31",
        "player_1": "Asatryan Murad",
        "player_1_url": "https://stats.sportgenerate.com/player/asatryan-murad/",
        "player_2": "Diaryan Aleksandr",
        "player_2_url": "https://stats.sportgenerate.com/player/diaryan-aleksandr/"
    }
]